{
  "cells": [
    {
      "shape": "edge",
      "attrs": {
        "line": {
          "stroke": "#A2B1C3"
        }
      },
      "id": "3a18e0f7-ea4f-4b8a-90fb-b989fa863da3",
      "zIndex": 0,
      "source": {
        "cell": "02b54140-3a0e-48fb-85c2-331929e873ed",
        "port": "db627c1c-019a-48fa-bb71-8968aec49ae8"
      },
      "target": {
        "cell": "df618d12-14de-47d0-9c5d-a6ac2b3f5dff",
        "port": "59d794dd-dfcf-45f7-94ee-cb14789177ff"
      }
    },
    {
      "shape": "edge",
      "attrs": {
        "line": {
          "stroke": "#A2B1C3"
        }
      },
      "id": "c0ceb3fc-f111-4b6a-a172-d45306aa7a8c",
      "zIndex": 0,
      "source": {
        "cell": "df618d12-14de-47d0-9c5d-a6ac2b3f5dff",
        "port": "db627c1c-019a-48fa-bb71-8968aec49ae8"
      },
      "target": {
        "cell": "c01f57a0-0df4-4c7d-be81-8b6edd051f79",
        "port": "59d794dd-dfcf-45f7-94ee-cb14789177ff"
      }
    },
    {
      "shape": "edge",
      "attrs": {
        "line": {
          "stroke": "#A2B1C3"
        }
      },
      "id": "c73e3d3a-2de8-4888-91f5-3303043a92b1",
      "zIndex": 0,
      "source": {
        "cell": "c01f57a0-0df4-4c7d-be81-8b6edd051f79",
        "port": "44380b1d-3651-4471-be45-970db0990350"
      },
      "target": {
        "cell": "76a841af-fb4f-4847-ab70-178e84e9800b",
        "port": "941cd036-e199-4596-a87f-7bdb11dc78e0"
      }
    },
    {
      "shape": "edge",
      "attrs": {
        "line": {
          "stroke": "#A2B1C3"
        }
      },
      "id": "65b6d7cf-b7a8-4bda-bc20-d3e98a4e6791",
      "zIndex": 0,
      "source": {
        "cell": "76a841af-fb4f-4847-ab70-178e84e9800b",
        "port": "59d794dd-dfcf-45f7-94ee-cb14789177ff"
      },
      "target": {
        "cell": "09ec290c-5b62-435b-a192-964562570fcd",
        "port": "db627c1c-019a-48fa-bb71-8968aec49ae8"
      }
    },
    {
      "shape": "edge",
      "attrs": {
        "line": {
          "stroke": "#A2B1C3"
        }
      },
      "id": "83a0fc40-774f-4fc4-b093-de28264d1007",
      "zIndex": 0,
      "source": {
        "cell": "09ec290c-5b62-435b-a192-964562570fcd",
        "port": "59d794dd-dfcf-45f7-94ee-cb14789177ff"
      },
      "target": {
        "cell": "959227f6-39a1-46aa-856e-06831f18b50e",
        "port": "db627c1c-019a-48fa-bb71-8968aec49ae8"
      }
    },
    {
      "shape": "edge",
      "attrs": {
        "line": {
          "stroke": "#A2B1C3"
        }
      },
      "id": "bf6c955e-cd64-4c84-a046-671fba81fd57",
      "zIndex": 0,
      "source": {
        "cell": "959227f6-39a1-46aa-856e-06831f18b50e",
        "port": "44380b1d-3651-4471-be45-970db0990350"
      },
      "target": {
        "cell": "48bd7920-ca56-4861-849c-3fdaa51efdca",
        "port": "941cd036-e199-4596-a87f-7bdb11dc78e0"
      }
    },
    {
      "shape": "edge",
      "attrs": {
        "line": {
          "stroke": "#A2B1C3"
        }
      },
      "id": "70e3664f-8db6-4172-9f33-d03f3421c85f",
      "zIndex": 0,
      "source": {
        "cell": "48bd7920-ca56-4861-849c-3fdaa51efdca",
        "port": "db627c1c-019a-48fa-bb71-8968aec49ae8"
      },
      "target": {
        "cell": "e4b2eb5a-aab2-414b-81be-a1fe47436ad9",
        "port": "59d794dd-dfcf-45f7-94ee-cb14789177ff"
      }
    },
    {
      "shape": "edge",
      "attrs": {
        "line": {
          "stroke": "#A2B1C3"
        }
      },
      "id": "23c50186-4e00-4508-96f0-267a70f910d1",
      "zIndex": 0,
      "source": {
        "cell": "e4b2eb5a-aab2-414b-81be-a1fe47436ad9",
        "port": "db627c1c-019a-48fa-bb71-8968aec49ae8"
      },
      "target": {
        "cell": "d8ba9fbc-c746-4fd5-94ed-20b696e933da",
        "port": "59d794dd-dfcf-45f7-94ee-cb14789177ff"
      }
    },
    {
      "position": {
        "x": -20,
        "y": 0
      },
      "size": {
        "width": 115,
        "height": 82
      },
      "view": "react-shape-view",
      "shape": "custom-react-shape",
      "ports": {
        "groups": {
          "top": {
            "position": "top",
            "attrs": {
              "circle": {
                "r": 4,
                "magnet": true,
                "stroke": "#5F95FF",
                "strokeWidth": 1,
                "fill": "#fff",
                "style": {
                  "visibility": "hidden"
                }
              }
            }
          },
          "right": {
            "position": "right",
            "attrs": {
              "circle": {
                "r": 4,
                "magnet": true,
                "stroke": "#5F95FF",
                "strokeWidth": 1,
                "fill": "#fff",
                "style": {
                  "visibility": "hidden"
                }
              }
            }
          },
          "bottom": {
            "position": "bottom",
            "attrs": {
              "circle": {
                "r": 4,
                "magnet": true,
                "stroke": "#5F95FF",
                "strokeWidth": 1,
                "fill": "#fff",
                "style": {
                  "visibility": "hidden"
                }
              }
            }
          },
          "left": {
            "position": "left",
            "attrs": {
              "circle": {
                "r": 4,
                "magnet": true,
                "stroke": "#5F95FF",
                "strokeWidth": 1,
                "fill": "#fff",
                "style": {
                  "visibility": "hidden"
                }
              }
            }
          }
        },
        "items": [
          {
            "group": "top",
            "id": "941cd036-e199-4596-a87f-7bdb11dc78e0"
          },
          {
            "group": "right",
            "id": "db627c1c-019a-48fa-bb71-8968aec49ae8"
          },
          {
            "group": "bottom",
            "id": "44380b1d-3651-4471-be45-970db0990350"
          },
          {
            "group": "left",
            "id": "59d794dd-dfcf-45f7-94ee-cb14789177ff"
          }
        ]
      },
      "id": "02b54140-3a0e-48fb-85c2-331929e873ed",
      "data": {
        "protoText": "Culture S. pombe cells in an appropriate medium."
      },
      "type": "textNode",
      "zIndex": 1
    },
    {
      "position": {
        "x": 180,
        "y": 11
      },
      "size": {
        "width": 160,
        "height": 60
      },
      "view": "react-shape-view",
      "shape": "custom-react-shape",
      "ports": {
        "groups": {
          "top": {
            "position": "top",
            "attrs": {
              "circle": {
                "r": 4,
                "magnet": true,
                "stroke": "#5F95FF",
                "strokeWidth": 1,
                "fill": "#fff",
                "style": {
                  "visibility": "hidden"
                }
              }
            }
          },
          "right": {
            "position": "right",
            "attrs": {
              "circle": {
                "r": 4,
                "magnet": true,
                "stroke": "#5F95FF",
                "strokeWidth": 1,
                "fill": "#fff",
                "style": {
                  "visibility": "hidden"
                }
              }
            }
          },
          "bottom": {
            "position": "bottom",
            "attrs": {
              "circle": {
                "r": 4,
                "magnet": true,
                "stroke": "#5F95FF",
                "strokeWidth": 1,
                "fill": "#fff",
                "style": {
                  "visibility": "hidden"
                }
              }
            }
          },
          "left": {
            "position": "left",
            "attrs": {
              "circle": {
                "r": 4,
                "magnet": true,
                "stroke": "#5F95FF",
                "strokeWidth": 1,
                "fill": "#fff",
                "style": {
                  "visibility": "hidden"
                }
              }
            }
          }
        },
        "items": [
          {
            "group": "top",
            "id": "941cd036-e199-4596-a87f-7bdb11dc78e0"
          },
          {
            "group": "right",
            "id": "db627c1c-019a-48fa-bb71-8968aec49ae8"
          },
          {
            "group": "bottom",
            "id": "44380b1d-3651-4471-be45-970db0990350"
          },
          {
            "group": "left",
            "id": "59d794dd-dfcf-45f7-94ee-cb14789177ff"
          }
        ]
      },
      "id": "df618d12-14de-47d0-9c5d-a6ac2b3f5dff",
      "data": {
        "protoText": "Harvest cells in a collection tube."
      },
      "type": "textNode",
      "zIndex": 2
    },
    {
      "position": {
        "x": 400,
        "y": 0
      },
      "size": {
        "width": 145,
        "height": 82
      },
      "view": "react-shape-view",
      "shape": "custom-react-shape",
      "ports": {
        "groups": {
          "top": {
            "position": "top",
            "attrs": {
              "circle": {
                "r": 4,
                "magnet": true,
                "stroke": "#5F95FF",
                "strokeWidth": 1,
                "fill": "#fff",
                "style": {
                  "visibility": "hidden"
                }
              }
            }
          },
          "right": {
            "position": "right",
            "attrs": {
              "circle": {
                "r": 4,
                "magnet": true,
                "stroke": "#5F95FF",
                "strokeWidth": 1,
                "fill": "#fff",
                "style": {
                  "visibility": "hidden"
                }
              }
            }
          },
          "bottom": {
            "position": "bottom",
            "attrs": {
              "circle": {
                "r": 4,
                "magnet": true,
                "stroke": "#5F95FF",
                "strokeWidth": 1,
                "fill": "#fff",
                "style": {
                  "visibility": "hidden"
                }
              }
            }
          },
          "left": {
            "position": "left",
            "attrs": {
              "circle": {
                "r": 4,
                "magnet": true,
                "stroke": "#5F95FF",
                "strokeWidth": 1,
                "fill": "#fff",
                "style": {
                  "visibility": "hidden"
                }
              }
            }
          }
        },
        "items": [
          {
            "group": "top",
            "id": "941cd036-e199-4596-a87f-7bdb11dc78e0"
          },
          {
            "group": "right",
            "id": "db627c1c-019a-48fa-bb71-8968aec49ae8"
          },
          {
            "group": "bottom",
            "id": "44380b1d-3651-4471-be45-970db0990350"
          },
          {
            "group": "left",
            "id": "59d794dd-dfcf-45f7-94ee-cb14789177ff"
          }
        ]
      },
      "id": "c01f57a0-0df4-4c7d-be81-8b6edd051f79",
      "data": {
        "protoText": "Suspend the cells with medium that was used in the culture of the cells "
      },
      "type": "textNode",
      "zIndex": 3
    },
    {
      "position": {
        "x": 407.5,
        "y": 140
      },
      "size": {
        "width": 130,
        "height": 82
      },
      "view": "react-shape-view",
      "shape": "custom-react-shape",
      "ports": {
        "groups": {
          "top": {
            "position": "top",
            "attrs": {
              "circle": {
                "r": 4,
                "magnet": true,
                "stroke": "#5F95FF",
                "strokeWidth": 1,
                "fill": "#fff",
                "style": {
                  "visibility": "hidden"
                }
              }
            }
          },
          "right": {
            "position": "right",
            "attrs": {
              "circle": {
                "r": 4,
                "magnet": true,
                "stroke": "#5F95FF",
                "strokeWidth": 1,
                "fill": "#fff",
                "style": {
                  "visibility": "hidden"
                }
              }
            }
          },
          "bottom": {
            "position": "bottom",
            "attrs": {
              "circle": {
                "r": 4,
                "magnet": true,
                "stroke": "#5F95FF",
                "strokeWidth": 1,
                "fill": "#fff",
                "style": {
                  "visibility": "hidden"
                }
              }
            }
          },
          "left": {
            "position": "left",
            "attrs": {
              "circle": {
                "r": 4,
                "magnet": true,
                "stroke": "#5F95FF",
                "strokeWidth": 1,
                "fill": "#fff",
                "style": {
                  "visibility": "hidden"
                }
              }
            }
          }
        },
        "items": [
          {
            "group": "top",
            "id": "941cd036-e199-4596-a87f-7bdb11dc78e0"
          },
          {
            "group": "right",
            "id": "db627c1c-019a-48fa-bb71-8968aec49ae8"
          },
          {
            "group": "bottom",
            "id": "44380b1d-3651-4471-be45-970db0990350"
          },
          {
            "group": "left",
            "id": "59d794dd-dfcf-45f7-94ee-cb14789177ff"
          }
        ]
      },
      "id": "76a841af-fb4f-4847-ab70-178e84e9800b",
      "data": {
        "protoText": "Add an equal amount of 0.7 N NaOH solution and mix well."
      },
      "type": "textNode",
      "zIndex": 4
    },
    {
      "position": {
        "x": 202.5,
        "y": 140
      },
      "size": {
        "width": 115,
        "height": 82
      },
      "view": "react-shape-view",
      "shape": "custom-react-shape",
      "ports": {
        "groups": {
          "top": {
            "position": "top",
            "attrs": {
              "circle": {
                "r": 4,
                "magnet": true,
                "stroke": "#5F95FF",
                "strokeWidth": 1,
                "fill": "#fff",
                "style": {
                  "visibility": "hidden"
                }
              }
            }
          },
          "right": {
            "position": "right",
            "attrs": {
              "circle": {
                "r": 4,
                "magnet": true,
                "stroke": "#5F95FF",
                "strokeWidth": 1,
                "fill": "#fff",
                "style": {
                  "visibility": "hidden"
                }
              }
            }
          },
          "bottom": {
            "position": "bottom",
            "attrs": {
              "circle": {
                "r": 4,
                "magnet": true,
                "stroke": "#5F95FF",
                "strokeWidth": 1,
                "fill": "#fff",
                "style": {
                  "visibility": "hidden"
                }
              }
            }
          },
          "left": {
            "position": "left",
            "attrs": {
              "circle": {
                "r": 4,
                "magnet": true,
                "stroke": "#5F95FF",
                "strokeWidth": 1,
                "fill": "#fff",
                "style": {
                  "visibility": "hidden"
                }
              }
            }
          }
        },
        "items": [
          {
            "group": "top",
            "id": "941cd036-e199-4596-a87f-7bdb11dc78e0"
          },
          {
            "group": "right",
            "id": "db627c1c-019a-48fa-bb71-8968aec49ae8"
          },
          {
            "group": "bottom",
            "id": "44380b1d-3651-4471-be45-970db0990350"
          },
          {
            "group": "left",
            "id": "59d794dd-dfcf-45f7-94ee-cb14789177ff"
          }
        ]
      },
      "id": "09ec290c-5b62-435b-a192-964562570fcd",
      "data": {
        "protoText": "Incubate at room temperature for 3 minutes."
      },
      "type": "textNode",
      "zIndex": 5
    },
    {
      "position": {
        "x": -7,
        "y": 140
      },
      "size": {
        "width": 145,
        "height": 82
      },
      "view": "react-shape-view",
      "shape": "custom-react-shape",
      "ports": {
        "groups": {
          "top": {
            "position": "top",
            "attrs": {
              "circle": {
                "r": 4,
                "magnet": true,
                "stroke": "#5F95FF",
                "strokeWidth": 1,
                "fill": "#fff",
                "style": {
                  "visibility": "hidden"
                }
              }
            }
          },
          "right": {
            "position": "right",
            "attrs": {
              "circle": {
                "r": 4,
                "magnet": true,
                "stroke": "#5F95FF",
                "strokeWidth": 1,
                "fill": "#fff",
                "style": {
                  "visibility": "hidden"
                }
              }
            }
          },
          "bottom": {
            "position": "bottom",
            "attrs": {
              "circle": {
                "r": 4,
                "magnet": true,
                "stroke": "#5F95FF",
                "strokeWidth": 1,
                "fill": "#fff",
                "style": {
                  "visibility": "hidden"
                }
              }
            }
          },
          "left": {
            "position": "left",
            "attrs": {
              "circle": {
                "r": 4,
                "magnet": true,
                "stroke": "#5F95FF",
                "strokeWidth": 1,
                "fill": "#fff",
                "style": {
                  "visibility": "hidden"
                }
              }
            }
          }
        },
        "items": [
          {
            "group": "top",
            "id": "941cd036-e199-4596-a87f-7bdb11dc78e0"
          },
          {
            "group": "right",
            "id": "db627c1c-019a-48fa-bb71-8968aec49ae8"
          },
          {
            "group": "bottom",
            "id": "44380b1d-3651-4471-be45-970db0990350"
          },
          {
            "group": "left",
            "id": "59d794dd-dfcf-45f7-94ee-cb14789177ff"
          }
        ]
      },
      "id": "959227f6-39a1-46aa-856e-06831f18b50e",
      "data": {
        "protoText": "Centrifuge the tube (5,000 rpm, 1 min) and discard the supernatant."
      },
      "type": "textNode",
      "zIndex": 6
    },
    {
      "position": {
        "x": 8,
        "y": 279
      },
      "size": {
        "width": 115,
        "height": 64
      },
      "view": "react-shape-view",
      "shape": "custom-react-shape",
      "ports": {
        "groups": {
          "top": {
            "position": "top",
            "attrs": {
              "circle": {
                "r": 4,
                "magnet": true,
                "stroke": "#5F95FF",
                "strokeWidth": 1,
                "fill": "#fff",
                "style": {
                  "visibility": "hidden"
                }
              }
            }
          },
          "right": {
            "position": "right",
            "attrs": {
              "circle": {
                "r": 4,
                "magnet": true,
                "stroke": "#5F95FF",
                "strokeWidth": 1,
                "fill": "#fff",
                "style": {
                  "visibility": "hidden"
                }
              }
            }
          },
          "bottom": {
            "position": "bottom",
            "attrs": {
              "circle": {
                "r": 4,
                "magnet": true,
                "stroke": "#5F95FF",
                "strokeWidth": 1,
                "fill": "#fff",
                "style": {
                  "visibility": "hidden"
                }
              }
            }
          },
          "left": {
            "position": "left",
            "attrs": {
              "circle": {
                "r": 4,
                "magnet": true,
                "stroke": "#5F95FF",
                "strokeWidth": 1,
                "fill": "#fff",
                "style": {
                  "visibility": "hidden"
                }
              }
            }
          }
        },
        "items": [
          {
            "group": "top",
            "id": "941cd036-e199-4596-a87f-7bdb11dc78e0"
          },
          {
            "group": "right",
            "id": "db627c1c-019a-48fa-bb71-8968aec49ae8"
          },
          {
            "group": "bottom",
            "id": "44380b1d-3651-4471-be45-970db0990350"
          },
          {
            "group": "left",
            "id": "59d794dd-dfcf-45f7-94ee-cb14789177ff"
          }
        ]
      },
      "id": "48bd7920-ca56-4861-849c-3fdaa51efdca",
      "data": {
        "protoText": "Add SDS-PAGE sample buffer and mix well."
      },
      "type": "textNode",
      "zIndex": 7
    },
    {
      "position": {
        "x": 210,
        "y": 279
      },
      "size": {
        "width": 100,
        "height": 64
      },
      "view": "react-shape-view",
      "shape": "custom-react-shape",
      "ports": {
        "groups": {
          "top": {
            "position": "top",
            "attrs": {
              "circle": {
                "r": 4,
                "magnet": true,
                "stroke": "#5F95FF",
                "strokeWidth": 1,
                "fill": "#fff",
                "style": {
                  "visibility": "hidden"
                }
              }
            }
          },
          "right": {
            "position": "right",
            "attrs": {
              "circle": {
                "r": 4,
                "magnet": true,
                "stroke": "#5F95FF",
                "strokeWidth": 1,
                "fill": "#fff",
                "style": {
                  "visibility": "hidden"
                }
              }
            }
          },
          "bottom": {
            "position": "bottom",
            "attrs": {
              "circle": {
                "r": 4,
                "magnet": true,
                "stroke": "#5F95FF",
                "strokeWidth": 1,
                "fill": "#fff",
                "style": {
                  "visibility": "hidden"
                }
              }
            }
          },
          "left": {
            "position": "left",
            "attrs": {
              "circle": {
                "r": 4,
                "magnet": true,
                "stroke": "#5F95FF",
                "strokeWidth": 1,
                "fill": "#fff",
                "style": {
                  "visibility": "hidden"
                }
              }
            }
          }
        },
        "items": [
          {
            "group": "top",
            "id": "941cd036-e199-4596-a87f-7bdb11dc78e0"
          },
          {
            "group": "right",
            "id": "db627c1c-019a-48fa-bb71-8968aec49ae8"
          },
          {
            "group": "bottom",
            "id": "44380b1d-3651-4471-be45-970db0990350"
          },
          {
            "group": "left",
            "id": "59d794dd-dfcf-45f7-94ee-cb14789177ff"
          }
        ]
      },
      "id": "e4b2eb5a-aab2-414b-81be-a1fe47436ad9",
      "data": {
        "protoText": "Heat at 95-100\u02daC for 5 min."
      },
      "type": "textNode",
      "zIndex": 8
    },
    {
      "position": {
        "x": 385,
        "y": 261
      },
      "size": {
        "width": 160,
        "height": 100
      },
      "view": "react-shape-view",
      "shape": "custom-react-shape",
      "ports": {
        "groups": {
          "top": {
            "position": "top",
            "attrs": {
              "circle": {
                "r": 4,
                "magnet": true,
                "stroke": "#5F95FF",
                "strokeWidth": 1,
                "fill": "#fff",
                "style": {
                  "visibility": "hidden"
                }
              }
            }
          },
          "right": {
            "position": "right",
            "attrs": {
              "circle": {
                "r": 4,
                "magnet": true,
                "stroke": "#5F95FF",
                "strokeWidth": 1,
                "fill": "#fff",
                "style": {
                  "visibility": "hidden"
                }
              }
            }
          },
          "bottom": {
            "position": "bottom",
            "attrs": {
              "circle": {
                "r": 4,
                "magnet": true,
                "stroke": "#5F95FF",
                "strokeWidth": 1,
                "fill": "#fff",
                "style": {
                  "visibility": "hidden"
                }
              }
            }
          },
          "left": {
            "position": "left",
            "attrs": {
              "circle": {
                "r": 4,
                "magnet": true,
                "stroke": "#5F95FF",
                "strokeWidth": 1,
                "fill": "#fff",
                "style": {
                  "visibility": "hidden"
                }
              }
            }
          }
        },
        "items": [
          {
            "group": "top",
            "id": "941cd036-e199-4596-a87f-7bdb11dc78e0"
          },
          {
            "group": "right",
            "id": "db627c1c-019a-48fa-bb71-8968aec49ae8"
          },
          {
            "group": "bottom",
            "id": "44380b1d-3651-4471-be45-970db0990350"
          },
          {
            "group": "left",
            "id": "59d794dd-dfcf-45f7-94ee-cb14789177ff"
          }
        ]
      },
      "id": "d8ba9fbc-c746-4fd5-94ed-20b696e933da",
      "data": {
        "protoText": "Centrifuge at at least 3,500 rpm, and use the supernatant as the total cell lysate."
      },
      "type": "textNode",
      "zIndex": 9
    }
  ]
}